<annotation>
	<folder>ImageSets</folder>
	<filename>201108120.jpg</filename>
	<path>E:\photo\00\ImageSets\201108120.jpg</path>
	<source>
		<database>Unknown</database>
	</source>
	<size>
		<width>282</width>
		<height>268</height>
		<depth>1</depth>
	</size>
	<segmented>0</segmented>
	<object>
		<name>CE</name>
		<pose>Unspecified</pose>
		<truncated>0</truncated>
		<difficult>0</difficult>
		<bndbox>
			<xmin>93</xmin>
			<ymin>50</ymin>
			<xmax>145</xmax>
			<ymax>103</ymax>
		</bndbox>
	</object>
</annotation>