<annotation>
	<folder>ImageSets</folder>
	<filename>201203230.jpg</filename>
	<path>E:\photo\00\ImageSets\201203230.jpg</path>
	<source>
		<database>Unknown</database>
	</source>
	<size>
		<width>484</width>
		<height>376</height>
		<depth>1</depth>
	</size>
	<segmented>0</segmented>
	<object>
		<name>CE</name>
		<pose>Unspecified</pose>
		<truncated>0</truncated>
		<difficult>0</difficult>
		<bndbox>
			<xmin>20</xmin>
			<ymin>20</ymin>
			<xmax>112</xmax>
			<ymax>110</ymax>
		</bndbox>
	</object>
	<object>
		<name>CE</name>
		<pose>Unspecified</pose>
		<truncated>0</truncated>
		<difficult>0</difficult>
		<bndbox>
			<xmin>383</xmin>
			<ymin>11</ymin>
			<xmax>440</xmax>
			<ymax>65</ymax>
		</bndbox>
	</object>
</annotation>