<annotation>
	<folder>ImageSets</folder>
	<filename>202004290.jpg</filename>
	<path>E:\photo\00\ImageSets\202004290.jpg</path>
	<source>
		<database>Unknown</database>
	</source>
	<size>
		<width>165</width>
		<height>156</height>
		<depth>1</depth>
	</size>
	<segmented>0</segmented>
	<object>
		<name>CE</name>
		<pose>Unspecified</pose>
		<truncated>0</truncated>
		<difficult>0</difficult>
		<bndbox>
			<xmin>132</xmin>
			<ymin>7</ymin>
			<xmax>157</xmax>
			<ymax>30</ymax>
		</bndbox>
	</object>
</annotation>
